redquery/__init__.py
redquery/cli.py
redquery/errors.py
redquery/formatting.py
redquery/models.py
redquery/redshift.py
redquery-0.1.0.dist-info/entry_points.txt
redquery-0.1.0.dist-info/WHEEL
redquery-0.1.0.dist-info/METADATA
redquery-0.1.0.dist-info/RECORD
