Metadata-Version: 2.1
Name: redquery
Version: 0.1.0
Summary: Run SQL queries against AWS Redshift via its Data API.
Author: Anatoly Scherbakov
Author-email: altaisoft@gmail.com
Requires-Python: >=3.8,<3.10
Classifier: Programming Language :: Python :: 3
Classifier: Programming Language :: Python :: 3.8
Classifier: Programming Language :: Python :: 3.9
Requires-Dist: boto3 (>=1.18.43,<2.0.0)
Requires-Dist: documented (>=0.1.1,<0.2.0)
Requires-Dist: mypy-boto3-redshift-data (>=1.18.43,<2.0.0)
Requires-Dist: typer (>=0.4.0,<0.5.0)
